<?xml version="1.0" encoding="UTF-8"?>
<?xml-stylesheet href="/xml/XSLT/panelfile-2-9-6.xsl" type="text/xsl"?>
<layout-config xmlns:xsi="http://www.w3.org/2001/XMLSchema-instance" xsi:noNamespaceSchemaLocation="http://jmri.org/xml/schema/layout-2-9-6.xsd">
  <jmriversion>
    <major>4</major>
    <minor>16</minor>
    <test>0</test>
    <modifier />
  </jmriversion>
  <sensors class="jmri.jmrix.internal.configurexml.InternalSensorManagerXml">
    <defaultInitialState>unknown</defaultInitialState>
    <sensor inverted="false">
      <systemName>ISCLOCKRUNNING</systemName>
    </sensor>
  </sensors>
  <turnouts class="jmri.jmrix.loconet.configurexml.LnTurnoutManagerXml">
    <operations automate="false">
      <operation name="NoFeedback" class="jmri.configurexml.turnoutoperations.NoFeedbackTurnoutOperationXml" interval="300" maxtries="2" />
      <operation name="Raw" class="jmri.configurexml.turnoutoperations.RawTurnoutOperationXml" interval="300" maxtries="1" />
      <operation name="Sensor" class="jmri.configurexml.turnoutoperations.SensorTurnoutOperationXml" interval="300" maxtries="3" />
    </operations>
    <defaultclosedspeed>Normal</defaultclosedspeed>
    <defaultthrownspeed>Restricted</defaultthrownspeed>
    <turnout feedback="MONITORING" inverted="false" automate="Off">
      <systemName>LT1</systemName>
      <userName>Turnout 1</userName>
    </turnout>
  </turnouts>
  <memories class="jmri.managers.configurexml.DefaultMemoryManagerXml">
    <memory value="2:39 PM">
      <systemName>IMCURRENTTIME</systemName>
    </memory>
    <memory value="1.0">
      <systemName>IMRATEFACTOR</systemName>
    </memory>
  </memories>
  <signalmasts class="jmri.managers.configurexml.DefaultSignalMastManagerXml" />
  <signalgroups class="jmri.managers.configurexml.DefaultSignalGroupManagerXml" />
  <oblocks class="jmri.jmrit.logix.configurexml.OBlockManagerXml" />
  <warrants class="jmri.jmrit.logix.configurexml.WarrantManagerXml" />
  <signalmastlogics class="jmri.managers.configurexml.DefaultSignalMastLogicManagerXml">
    <logicDelay>500</logicDelay>
  </signalmastlogics>
  <timebase class="jmri.jmrit.simpleclock.configurexml.SimpleTimebaseXml" time="Sun Sep 15 14:29:03 CDT 2019" rate="1.0" startrate="1.0" run="yes" master="yes" sync="no" correct="no" display="no" startstopped="no" startrunning="yes" startsettime="no" startclockoption="0" showbutton="no" startsetrate="yes" />
  <LayoutEditor class="jmri.jmrit.display.layoutEditor.configurexml.LayoutEditorXml" name="My Layout" x="1" y="204" windowheight="846" windowwidth="1680" panelheight="930" panelwidth="1661" sliders="no" scrollable="none" editable="yes" positionable="yes" controlling="yes" animating="yes" showhelpbar="no" drawgrid="yes" snaponadd="no" snaponmove="no" antialiasing="no" turnoutcircles="no" tooltipsnotedit="no" tooltipsinedit="yes" mainlinetrackwidth="4" xscale="1.0" yscale="1.0" sidetrackwidth="2" defaulttrackcolor="darkGray" defaultoccupiedtrackcolor="red" defaultalternativetrackcolor="white" defaulttextcolor="black" turnoutcirclecolor="black" turnoutcirclesize="4" turnoutdrawunselectedleg="yes" turnoutbx="20.0" turnoutcx="20.0" turnoutwid="10.0" xoverlong="30.0" xoverhwid="10.0" xovershort="10.0" autoblkgenerate="no" redBackground="192" greenBackground="192" blueBackground="192" gridSize="10" gridSize2nd="10" openDispatcher="no" useDirectTurnoutControl="no">
    <layoutTrackDrawingOptions name="My Layout" class="jmri.jmrit.display.layoutEditor.configurexml.LayoutTrackDrawingOptionsXml">
      <mainBallastColor>#000000</mainBallastColor>
      <mainBallastWidth>0</mainBallastWidth>
      <mainBlockLineDashPercentageX10>0</mainBlockLineDashPercentageX10>
      <mainBlockLineWidth>4</mainBlockLineWidth>
      <mainRailColor>#404040</mainRailColor>
      <mainRailCount>1</mainRailCount>
      <mainRailGap>0</mainRailGap>
      <mainRailWidth>2</mainRailWidth>
      <mainTieColor>#000000</mainTieColor>
      <mainTieGap>0</mainTieGap>
      <mainTieLength>0</mainTieLength>
      <mainTieWidth>0</mainTieWidth>
      <sideBallastColor>#000000</sideBallastColor>
      <sideBallastWidth>0</sideBallastWidth>
      <sideBlockLineDashPercentageX10>0</sideBlockLineDashPercentageX10>
      <sideBlockLineWidth>2</sideBlockLineWidth>
      <sideRailColor>#404040</sideRailColor>
      <sideRailCount>1</sideRailCount>
      <sideRailGap>0</sideRailGap>
      <sideRailWidth>1</sideRailWidth>
      <sideTieColor>#000000</sideTieColor>
      <sideTieGap>0</sideTieGap>
      <sideTieLength>0</sideTieLength>
      <sideTieWidth>0</sideTieWidth>
    </layoutTrackDrawingOptions>
    <layoutturnout ident="TO2" type="1" hidden="no" disabled="no" disableWhenOccupied="no" continuing="2" xcen="500.0" ycen="202.0" xa="480.0" ya="202.0" xb="520.0" yb="202.0" xc="520.0" yc="212.0" xd="480.0" yd="202.0" ver="1" class="jmri.jmrit.display.layoutEditor.configurexml.LayoutTurnoutXml" turnoutname="Turnout 1" />
  </LayoutEditor>
  <filehistory>
    <operation>
      <type>app</type>
      <date>Sun Sep 15 14:29:02 CDT 2019</date>
      <filename>JMRI program</filename>
    </operation>
    <operation>
      <type>Store</type>
      <date>Sun Sep 15 14:39:14 CDT 2019</date>
      <filename />
    </operation>
  </filehistory>
  <!--Written by JMRI version 4.16+R6f9aced on Sun Sep 15 14:39:14 CDT 2019-->
</layout-config>
